youtube_ai_resume/caption.py
youtube_ai_resume/cli.py
youtube_ai_resume/config.py
youtube_ai_resume/speech.py
youtube_ai_resume/summarizer.py
youtube_ai_resume-0.0.17.dist-info/METADATA
youtube_ai_resume-0.0.17.dist-info/WHEEL
youtube_ai_resume-0.0.17.dist-info/entry_points.txt
youtube_ai_resume-0.0.17.dist-info/licenses/LICENCE
youtube_ai_resume-0.0.17.dist-info/RECORD
