Metadata-Version: 2.4
Name: youtube-ai-resume
Version: 0.0.17
Summary: CLI & library that extracts YouTube captions and returns an OpenAI-generated summary
Author-email: Fábio Berbert de Paula <fberbert@gmail.com>
License: MIT
License-File: LICENCE
Classifier: Programming Language :: Python :: 3
Classifier: Programming Language :: Python :: 3.9
Classifier: Programming Language :: Python :: 3.10
Classifier: Programming Language :: Python :: 3.11
Classifier: Programming Language :: Python :: 3.12
Requires-Python: >=3.9
Requires-Dist: beautifulsoup4>=4.12
Requires-Dist: google-cloud-texttospeech>=2.16
Requires-Dist: openai>=1.15
Requires-Dist: playsound>=1.3
Requires-Dist: prompt-toolkit>=3.0
Requires-Dist: protobuf<4,>=3.20
Requires-Dist: requests>=2.32
Requires-Dist: rich>=13.7
Requires-Dist: youtube-transcript-api
Provides-Extra: dev
Requires-Dist: build; extra == 'dev'
Requires-Dist: pytest; extra == 'dev'
Requires-Dist: ruff; extra == 'dev'
Requires-Dist: twine; extra == 'dev'
